<?xml version="1.0" encoding="UTF-8"?>
<song xmlns="http://openlyrics.info/namespace/2009/song" version="0.8" createdIn="ConvDiatarOpenlyrics" modifiedIn="ConvDiatarOpenlyrics" modifiedDate="2015-06-09T16:45:31">
  <properties>
    <titles>
      <title>Requiem æternam dona eis</title>
    </titles>
    <verseOrder>v1 v2 v3</verseOrder>
    <songbooks>
      <songbook name="Éneklő Egyház" entry="686"/>
    </songbooks>
  </properties>
  <lyrics>
    <verse name="v1">
      <lines>Requiem æternam dona eis Domine:<br/>et lux perpetua luceat eis.</lines>
    </verse>
    <verse name="v2">
      <lines>Te decet hymnus Deus in Sion et tibi reddetur votum in Jerusalem,<br/>exaudi orationem meam, ad te omnis caro veniet.</lines>
    </verse>
    <verse name="v3">
      <lines>Requiem æternam dona eis Domine:<br/>et lux perpetua luceat eis.</lines>
    </verse>
  </lyrics>
</song>
