<?xml version="1.0"?>
<song xmlns="http://openlyrics.info/namespace/2009/song" version="0.8" createdIn="ConvDiatarOpenlyrics" modifiedIn="ConvDiatarOpenlyrics" modifiedDate="2015-06-09T16:45:49">
  <properties>
    <titles>
      <title>Graduale [ÉE 658]</title>
    </titles>
    <verseOrder>v1</verseOrder>
    <authors>
      <author></author>
    </authors>
    <songbooks>
      <songbook name="Graduale Hungaricum" entry="445"/>
    </songbooks>
  </properties>
  <lyrics>
    <verse name="v1">
      <lines>Az igaz lelkek az Úr kezében vannak,<br/>a gonoszok kínzása nem éri őket.</lines>
    </verse>
  </lyrics>
</song>
