<?xml version="1.0"?>
<song xmlns="http://openlyrics.info/namespace/2009/song" version="0.8" createdIn="ConvDiatarOpenlyrics" modifiedIn="ConvDiatarOpenlyrics" modifiedDate="2014-05-23T15:25:37">
  <properties>
    <titles>
      <title>Székely dal</title>
    </titles>
    <verseOrder>v1 v2 v3</verseOrder>
    <authors>
      <author></author>
    </authors>
    <songbooks>
      <songbook name="Cserkészek daloskönyve" entry="111"/>
    </songbooks>
  </properties>
  <lyrics>
    <verse name="v1">
      <lines>Én Istenem, jó Istenem,<br/>Oltalmazó segedelmem.<br/>Vándorlásban reménységem,<br/>Ínségemben lágy kenyerem.</lines>
    </verse>
    <verse name="v2">
      <lines>Vándorfecske sebes szárnyát,<br/>Vándorlegény vándorbotját,<br/>Vándor székely reménységét,<br/>Jézus, áldd meg Erdély földjét!</lines>
    </verse>
    <verse name="v3">
      <lines>Vándorfecske hazatalál,<br/>Édesanyja fészkére száll;<br/>Hazamegyünk, megsegít a<br/>Csíksomlyói Szűz Mária.</lines>
    </verse>
  </lyrics>
</song>
