<?xml version='1.0' encoding='UTF-8'?>
<song xmlns="http://openlyrics.info/namespace/2009/song" version="0.8" createdIn="OpenLP 2.4.6" modifiedIn="OpenLP 2.4.6" modifiedDate="2019-10-01T15:02:58">
  <properties>
    <titles>
      <title>179. Ez az a nap</title>
    </titles>
    <authors>
      <author>Author Unknown</author>
    </authors>
  </properties>
  <lyrics>
    <verse name="v1a">
      <lines>1/3. Ez az a nap, ez az a nap,<br/>Mit az Úr szerzett, mit az Úr szerzett. <br/>Ez az a nap, ez az a nap, <br/>Mit az Úr szerzett, mit az Úr szerzett.</lines>
    </verse>
    <verse name="v1b">
      <lines>Örvendjünk, vigadjunk e napon! <br/>Örvendjünk, vigadjunk e napon! <br/>Ez az a nap, ez az a nap<br/>mit az Úr szerzett.</lines>
    </verse>
    <verse name="v2a">
      <lines>2/3. Jézus az Úr, Jézus az Úr,<br/>Akit szolgálunk, Akit szolgálunk. <br/>Jézus az Úr, Jézus az Úr, <br/>Akit szolgálunk, Akit szolgálunk.</lines>
    </verse>
    <verse name="v2b">
      <lines>Szolgáljuk hűséggel szent Nevét!<br/>Szolgáljuk hűséggel szent Nevét! <br/>Jézus az Úr, Jézus az Úr <br/>Akit szolgálunk.</lines>
    </verse>
    <verse name="v3a">
      <lines>3/3.Eljön az Úr, eljön az Úr, <br/>Akit úgy várunk, Akit úgy várunk. <br/>Eljön az Úr, eljön az Úr<br/>Akit úgy várunk, Akit úgy várunk.</lines>
    </verse>
    <verse name="v3b">
      <lines>Egy szívvel mondjuk,hogy Jöjj újra már! <br/>Egy szívvel mondjuk, <br/>hogy Jöjj újra már! <br/>Jövel, Uram, jövel, Uram, jövel, Úr Jézus!</lines>
    </verse>
  </lyrics>
</song>
