<?xml version="1.0" encoding="UTF-8"?>
<song xmlns="http://openlyrics.info/namespace/2009/song" version="0.8" createdIn="OpenLP 2.4.6" modifiedIn="OpenLP 2.4.6" modifiedDate="2019-10-01T15:02:54">
  <properties>
    <titles>
      <title>A keresztfához megyek</title>
    </titles>
    <authors>
      <author>ismeretlen szerző</author>
    </authors>
    <songbooks>
      <songbook name="A Hit Hangjai" entry="022"/>
    </songbooks>
  </properties>
  <lyrics>
    <verse name="v1">
      <lines>1/4. A keresztfához megyek, Mert máshol nem lelhetek<br/>Nyugodalmat lelkemnek.<br/>Ott könnyárban leborulok, Bűnterhemtől szabadulok,<br/>Hol a bűntelen szenved.</lines>
    </verse>
    <verse name="v2">
      <lines>2/4. Isten ama Báránya Hogy jut a keresztfára?<br/>Mért foly alá szent vére?<br/>Értem tette ezt Jézusom, Fájó szívvel hiszem, tudom,<br/>Lelkem örök üdvére.</lines>
    </verse>
    <verse name="v3">
      <lines>3/4. Én voltam az elveszett, Aki halált érdemelt,<br/>Kire gyászos éj szakadt.<br/>Isten Fia, a jó Pásztor, Megváltott a bűn átkától,<br/>Üdvöm, napom föltámadt.</lines>
    </verse>
    <verse name="v4">
      <lines>4/4. Csodás égi szeretet! Szívem mindent elfeled,<br/>Ami eddig földre vont.<br/>Csak rád nézek, én Megváltóm, Kegyelmedet sírig áldom,<br/>Óemberem már megholt.</lines>
    </verse>
    <verse name="v5">
      <lines>Tied vagyok, Jézusom, Megyek keresztútadon,<br/>Nyugtot, békét így lelek.<br/>A szeretet hozzád kapcsol, - Boldog, aki híven harcol. - <br/>Veled mindig győzhetek!</lines>
    </verse>
  </lyrics>
</song>
