<?xml version="1.0" encoding="UTF-8"?>
<song xmlns="http://openlyrics.info/namespace/2009/song" version="0.8" createdIn="OpenLP 2.4.6" modifiedIn="OpenLP 2.4.6" modifiedDate="2019-10-01T15:03:02">
  <properties>
    <titles>
      <title>Istennek népe, készen légy</title>
    </titles>
    <authors>
      <author>ismeretlen szerző</author>
    </authors>
    <songbooks>
      <songbook name="A Hit Hangjai" entry="311"/>
    </songbooks>
  </properties>
  <lyrics>
    <verse name="v1">
      <lines>1. Istennek népe, készen légy,<br/>Az Úr nagy napja jön feléd! <br/>A Vőlegény nincs messze már, <br/>Felékesítve várj!</lines>
    </verse>
    <verse name="c1">
      <lines>Refrén:<br/>Oly dicső lesz az a nap, <br/>Oly dicső lesz az a nap ! <br/>Jövel hamar, jövel, Uram, <br/>Hozd fel nagy napodat!</lines>
    </verse>
    <verse name="v2">
      <lines>2. Istennek népe, ne heverj,<br/>A leghasznos'b munkára fel, <br/>Az Úr napja nincs messze már, <br/>Munkád végezve várj!</lines>
    </verse>
    <verse name="v3">
      <lines>3. Istennek népe, ne feledd, <br/>Mire az Úr int tégedet, <br/>Hogy hirtelen jő el a nap, <br/>Egy pillanat alatt!</lines>
    </verse>
  </lyrics>
</song>
