<?xml version="1.0" encoding="UTF-8"?>
<song xmlns="http://openlyrics.info/namespace/2009/song" version="0.8" createdIn="OpenLP 2.4.6" modifiedIn="OpenLP 2.4.6" modifiedDate="2019-10-01T15:03:02">
  <properties>
    <titles>
      <title>Itt az éltem, Jézusom</title>
    </titles>
    <authors>
      <author>ismeretlen szerző</author>
    </authors>
    <songbooks>
      <songbook name="A Hit Hangjai" entry="324"/>
    </songbooks>
  </properties>
  <lyrics>
    <verse name="v1">
      <lines>1. Itt az éltem, Jézusom, <br/>Oltárodra áldozom. <br/>Néked adom kezemet,<br/>Építsd vele művedet, <br/>Építsd vele művedet!.</lines>
    </verse>
    <verse name="v2">
      <lines>2. Add, hogy lábam gyors legyen, <br/>Hogy szent Igéd terjedjen!<br/>Add, hogy hangom zengje most <br/>Üdvre hívó szózatod,<br/>Üdvre hívó szózatod!</lines>
    </verse>
    <verse name="v3">
      <lines>3. Lelkem minden szándékát<br/>Kedved szerint Te formáld!<br/>Itt a szívem, Jézusom, <br/>Legyen szentelt templomod,<br/>Legyen szentelt templomod.</lines>
    </verse>
  </lyrics>
</song>
