<?xml version='1.0' encoding='UTF-8'?>
<song xmlns="http://openlyrics.info/namespace/2009/song" version="0.8" createdIn="OpenLP 2.4.6" modifiedIn="OpenLP 2.4.6" modifiedDate="2019-10-01T15:03:04">
  <properties>
    <titles>
      <title>Jézus szent Nevérõl</title>
    </titles>
    <authors>
      <author>ismeretlen szerző</author>
    </authors>
    <songbooks>
      <songbook name="A Hit Hangjai" entry="379"/>
    </songbooks>
  </properties>
  <lyrics>
    <verse name="v1">
      <lines>1. Jézus szent Nevéről <br/>úgy szeretnék szólni, <br/>Benne szívem <br/>igaz barátra talált. <br/>Szava átformálta életem egészen, <br/>Senki nem szeret úgy, <br/>mint e hű barát.</lines>
    </verse>
    <verse name="c1">
      <lines>Refrén:<br/>Nincsen olyan jó barát, mint Jézus! <br/>Nincsen senki olyan jó, <br/>mint Ő!<br/>Bűntől megszabadít, <br/>gondot visel rólam, <br/>Engem nagyon szeret Ő.</lines>
    </verse>
    <verse name="v2">
      <lines>2. Bűnben megkötözve, <br/>nagy nyomorban éltem, <br/>Mikor Jézus Krisztus engem megtalált; <br/>Karját szeretettel <br/>kinyújtotta értem, <br/>Akkor megismertem mentő hatalmát.</lines>
    </verse>
    <verse name="v3">
      <lines>3. Napról napra biztosít szeretetéről, <br/>Jobban, egyre jobban értem szent szavát; <br/>Szívem minden vágyát betölti egészen, <br/>Majd, ha színről színre látom szent arcát.</lines>
    </verse>
  </lyrics>
</song>
