<?xml version='1.0' encoding='UTF-8'?>
<song xmlns="http://openlyrics.info/namespace/2009/song" version="0.8" createdIn="OpenLP 2.4.6" modifiedIn="OpenLP 2.4.6" modifiedDate="2019-10-01T15:03:06">
  <properties>
    <titles>
      <title>Maradj velem</title>
    </titles>
    <authors>
      <author>ismeretlen szerző</author>
    </authors>
    <songbooks>
      <songbook name="A Hit Hangjai" entry="459"/>
    </songbooks>
  </properties>
  <lyrics>
    <verse name="v1">
      <lines>1. Maradj velem, mert immár alkonyul, <br/>Az éjszakának sötét árnya hull! <br/>Aki segítne, <br/>senkim sincs nekem, <br/>Ó, szánj meg, Uram, és maradj velem!</lines>
    </verse>
    <verse name="v2">
      <lines>2. Amint a napfény eltűnt lassúdan, <br/>Földi dicsőség, öröm elsuhan, <br/>Mert csak mulandó minden idelenn, <br/>Ó, Te, ki örök vagy, maradj velem!</lines>
    </verse>
    <verse name="v3">
      <lines>3. Minden órában <br/>vágylak Tégedet, <br/>Nagy irgalmadat, <br/>szent szerelmedet; <br/>Ha beszélsz hozzám, <br/>gerjedez szívem, <br/>Uram, Vigasztalóm, <br/>maradj velem!</lines>
    </verse>
    <verse name="v4">
      <lines>4. Tárd ki felettem <br/>áldó szent kezed, <br/>S én megcsókolom rajt' a sebhelyet… <br/>Földi éj múlik, <br/>de fény gyúl mennyben, <br/>Halál völgyén <br/>túl is maradj velem!</lines>
    </verse>
  </lyrics>
</song>
