<?xml version="1.0"?>
<song xmlns="http://openlyrics.info/namespace/2009/song" version="0.8" createdIn="ConvDiatarOpenlyrics" modifiedIn="ConvDiatarOpenlyrics" modifiedDate="2014-05-23T16:27:44">
  <properties>
    <titles>
      <title>Táncolj az Úrnak</title>
    </titles>
    <verseOrder>v1 v2 v3 v4</verseOrder>
    <authors>
      <author></author>
    </authors>
    <songbooks>
      <songbook name="Kék Könyv" entry="269"/>
    </songbooks>
  </properties>
  <lyrics>
    <verse name="v1">
      <lines>Táncolj az Úrnak, dicsérjed nevét, ujjogj, hisz Ő a te megváltód!</lines>
    </verse>
    <verse name="v2">
      <lines>Mint Dávid az Úr ládája előtt, táncoljunk Istennek!<br/>Az Ő országa már köztünk van, daloljon ajkunk ujjongva!<br/>Ref.</lines>
    </verse>
    <verse name="v3">
      <lines>Mint Mária Erzsébet házában,<br/>örvend a bensőm hálával.<br/>A Lélek a szívemet eltölti, alleluja; így zengi!<br/>Ref.</lines>
    </verse>
    <verse name="v4">
      <lines>Kik kedvesen az Úrnak, dicsérik Őt,<br/>Hűségükkel szolgálnak.<br/>Mint betlehemi nyájak pásztorai,<br/>hódoljunk színe előtt!<br/>Ref.</lines>
    </verse>
  </lyrics>
</song>
