<?xml version='1.0' encoding='UTF-8'?>
<song xmlns="http://openlyrics.info/namespace/2009/song" version="0.8" createdIn="OpenLP 2.4.6" modifiedIn="OpenLP 2.4.6" modifiedDate="2019-10-01T15:03:33">
  <properties>
    <titles>
      <title>Z171 Hallottal-e arrol</title>
    </titles>
    <authors>
      <author>Author Unknown</author>
    </authors>
  </properties>
  <lyrics>
    <verse name="v1">
      <lines>Hallottál-e arról, hogy Jézus újra visszajön,<br/>Hogy Jézus újra visszajön?<br/>Hallottál-e arról, hogy nemsokára <br/>újra visszajön,<br/>Hogy nemsokára újra visszajön?<br/>/:Egy nap, amit úgy vár a szívem,<br/>Hogy Jézus innen elvigyen.:/</lines>
    </verse>
  </lyrics>
</song>
