<?xml version="1.0"?>
<song xmlns="http://openlyrics.info/namespace/2009/song" version="0.8" createdIn="ConvDiatarOpenlyrics" modifiedIn="ConvDiatarOpenlyrics" modifiedDate="2015-06-09T16:45:59">
  <properties>
    <titles>
      <title>Hál Istennek, elvégeztük</title>
    </titles>
    <verseOrder>v1 v2 v3</verseOrder>
    <authors>
      <author></author>
    </authors>
    <songbooks>
      <songbook name="Harmatozzatok, egek!" entry="170b"/>
    </songbooks>
  </properties>
  <lyrics>
    <verse name="v1">
      <lines>Hál' Istennek, elvégeztük szent búcsújárásunkat,<br/>Melyet egek homlokára lángfohásszal írtunk.<br/>Vedd kedvesen, Szűz Mária, ájtatos, szép virág,<br/>Megjelenésed emlékét tartja ezen ország.</lines>
    </verse>
    <verse name="v2">
      <lines>Ó, kegyelemnek tengere, áldásoknak forrása,<br/>Bő malasztod szent érdeme szálljon mindnyájunkra.<br/>A csillagok százezrei mind csak azt jelentik,<br/>Egy fénysugár lent a földön, imáját rebegi.</lines>
    </verse>
    <verse name="v3">
      <lines>Úgy a mennyben, úgy a földön nagy híre van ennek,<br/>A lurdesi ájtatosság búcsúkegyelmének.</lines>
    </verse>
  </lyrics>
</song>
