<?xml version="1.0" encoding="UTF-8"?>
<song xmlns="http://openlyrics.info/namespace/2009/song" version="0.8" createdIn="ConvDiatarOpenlyrics" modifiedIn="ConvDiatarOpenlyrics" modifiedDate="2015-06-09T16:45:59">
  <properties>
    <titles>
      <title>Szép, ragyogó napunk támadt</title>
    </titles>
    <verseOrder>v1 v2 v3 v4 v5</verseOrder>
    <authors>
      <author></author>
    </authors>
    <songbooks>
      <songbook name="Harmatozzatok, egek!" entry="102"/>
    </songbooks>
  </properties>
  <lyrics>
    <verse name="v1">
      <lines>Szép, ragyogó napunk támadt,<br/>Mivel Krisztus ma feltámadt.<br/>Örvendjünk, vigadjunk,<br/>Rebegje hőn ajkunk:<br/>Alle-, alleluja!</lines>
    </verse>
    <verse name="v2">
      <lines>A hívők mind együtt voltak,<br/>És könnyezték a nagy holtat.<br/>Közöttük, ím, egyszer<br/>Megjelent a Mester,<br/>Alle-, alleluja!</lines>
    </verse>
    <verse name="v3">
      <lines>Egy angyal ült fényben ottan,<br/>S szólt hozzájuk meghatottan:<br/>Nincs már itt, feltámadt,<br/>Múljék el a bánat,<br/>Alle-, alleluja!</lines>
    </verse>
    <verse name="v4">
      <lines>Jézus szent feltámadása<br/>Annak legfőbb bizonysága,<br/>Hogy mi is majd egykor<br/>Fölkelünk a sírból,<br/>Alle-, alleluja!</lines>
    </verse>
    <verse name="v5">
      <lines>Leborulunk és imádunk,<br/>Ó, feltámadt, nagy királyunk.<br/>Ha nyílik sírhalmunk,<br/>Légy mennyben jutalmunk,<br/>Alle-, alleluja!</lines>
    </verse>
  </lyrics>
</song>
