<?xml version='1.0' encoding='UTF-8'?>
<song xmlns="http://openlyrics.info/namespace/2009/song" version="0.8" createdIn="OpenLP 2.0.1" modifiedIn="OpenLP 2.0.1" modifiedDate="2013-02-06T21:40:10">
  <properties>
    <titles>
      <title>Szent színed elé</title>
    </titles>
    <verseOrder>v1 c1</verseOrder>
    <authors>
      <author>ismeretlen</author>
    </authors>
    <songbooks>
      <songbook name="Énekfüzet" entry="92"/>
    </songbooks>
  </properties>
  <lyrics>
    <verse name="v1">
      <lines>Szent színed elé járulunk, hogy hódoljunk Neked,<br/>hálával áldozzunk, magasztaljuk nagy neved.<br/>Mert megmentetted népedet, új életet adtál,<br/>fogadd el szívünk buzgó szeretetének dalát!</lines>
    </verse>
    <verse name="c1">
      <lines>Te vagy az Istennek Báránya, a Magasságos Fia,<br/>aki kilépett a sírból, a halál nem fogott rajta.<br/>Szabadítónk lettél nékünk, Benned van reményünk,<br/>nincs másban üdvösség, Tied minden dicsőség!</lines>
    </verse>
  </lyrics>
</song>
