<?xml version="1.0"?>
<song xmlns="http://openlyrics.info/namespace/2009/song" version="0.8" createdIn="ConvDiatarOpenlyrics" modifiedIn="ConvDiatarOpenlyrics" modifiedDate="2014-05-23T16:34:24">
  <properties>
    <titles>
      <title>Kiáltsátok: Alleluja</title>
    </titles>
    <verseOrder>v1 v2 v3 v4 v5</verseOrder>
    <authors>
      <author></author>
    </authors>
    <songbooks>
      <songbook name="ZöldKönyv" entry="29"/>
    </songbooks>
  </properties>
  <lyrics>
    <verse name="v1">
      <lines>‖: Kiáltsátok: Alleluja! Kiáltsátok: Alleluja!<br/>Kiáltsátok: Alleluja az Isten szent nevét! :‖</lines>
    </verse>
    <verse name="v2">
      <lines>Bánatunk messze elszaladt,<br/>Friss hajnal kél az ég alatt,<br/>S remény fakad sírboltok sötét rejtekén,<br/>Eláraszt mindent már a fény -<br/>Soha nem látott, gyönyörű égi fény.</lines>
    </verse>
    <verse name="v3">
      <lines>‖: Kiáltsátok: Alleluja! Kiáltsátok: Alleluja!<br/>Kiáltsátok: Alleluja az Isten szent nevét! :‖</lines>
    </verse>
    <verse name="v4">
      <lines>Illattal terhes szél dalol,<br/>Világok titkán áthatol,<br/>Hozzád hajol, s így bíztat. -<br/>Nincs mit félni már,<br/>Meghalt végleg minden halál!</lines>
    </verse>
    <verse name="v5">
      <lines>‖: Kiáltsátok: Alleluja! Kiáltsátok: Alleluja!<br/>Kiáltsátok: Alleluja az Isten szent nevét! :‖</lines>
    </verse>
  </lyrics>
</song>
