<?xml version="1.0" encoding="UTF-8"?>
<song xmlns="http://openlyrics.info/namespace/2009/song" version="0.8" createdIn="OpenLP 2.4.6" modifiedIn="OpenLP 2.4.6" modifiedDate="2019-10-01T15:03:19">
  <properties>
    <titles>
      <title>Gyermekkent jott</title>
    </titles>
    <authors>
      <author>ismeretlen szerző</author>
    </authors>
  </properties>
  <lyrics>
    <verse name="v1">
      <lines>Gyermekként jött, égi lény,<br/>Glória nélkül érkeztél.<br/>Te szolgáltál minekünk,<br/>Halálod által élhetünk.</lines>
    </verse>
    <verse name="c1">
      <lines>Íme, az Úr, Szolga-király,<br/>Most minket hív, kövessük hát!<br/>Hozzuk Elé szívünk hódolatát,<br/>Imádjuk a Szolga-királyt!</lines>
    </verse>
    <verse name="v2">
      <lines>Egy kertben sírt, könnyezett,<br/>Miattam hordott bűnterhet.<br/>Megtört szívvel mondta ott:<br/>„Legyen, Atyám, akaratod.”</lines>
    </verse>
    <verse name="v3">
      <lines>Jöjj hát, és nézd sebeit,<br/>Áldozatáról hirdetik:<br/>Eget tartó nagy kezét<br/>Kínzó szegeknek tárta szét.</lines>
    </verse>
    <verse name="v4">
      <lines>Szolgálni Ő megtanít,<br/>Szívünknek trónján Ő lakik.<br/>Ha fölvesszük más baját,<br/>Akkor szolgáljuk Őt, magát.</lines>
    </verse>
  </lyrics>
</song>
