<?xml version="1.0" encoding="UTF-8"?>
<song xmlns="http://openlyrics.info/namespace/2009/song" version="0.8" createdIn="OpenLP 2.4.6" modifiedIn="OpenLP 2.4.6" modifiedDate="2019-10-01T15:03:21">
  <properties>
    <titles>
      <title>Jezusom aldozatodra gondolok</title>
    </titles>
    <authors>
      <author>ismeretlen szerző</author>
    </authors>
  </properties>
  <lyrics>
    <verse name="v1">
      <lines>Jézusom, áldozatodra gondolok,<br/>meghaltál értem a Golgotán.<br/>Te mindig vársz,<br/>hátat soha nem fordítanál,<br/>most újra itt vagyok.<br/>Most újra itt vagyok.</lines>
    </verse>
    <verse name="c1">
      <lines>Drága véred értem folyt<br/>ott fent a keresztfán,<br/>alázattal térdre hullok<br/>kegyelmed láttán.<br/>Most újra hálás szívem,<br/>újra leteszem életem.</lines>
    </verse>
    <verse name="v2">
      <lines>Most magasra emelem fel Szent Neved,<br/>hisz csak Te vagy méltó,<br/>Megváltó Úr.<br/>Csodálom megmentő kegyelmedet,<br/>és imádom Szent Neved.<br/>És imádom Szent Neved.</lines>
    </verse>
    <verse name="b1">
      <lines>Köszönöm Neked, <br/>köszönöm Neked,<br/>köszönöm Neked, a keresztet! (4x)</lines>
    </verse>
  </lyrics>
</song>
