<?xml version='1.0' encoding='UTF-8'?>
<song xmlns="http://openlyrics.info/namespace/2009/song" version="0.8" createdIn="OpenLP 2.4.6" modifiedIn="OpenLP 2.4.6" modifiedDate="2019-10-01T15:03:22">
  <properties>
    <titles>
      <title>Jovok a kereszthez</title>
    </titles>
    <authors>
      <author>Author Unknown</author>
    </authors>
  </properties>
  <lyrics>
    <verse name="c1">
      <lines>Jövök a kereszthez...Jövök a kereszthez...<br/>Neked halált hozott, nekem életet. Jövök a kereszthez... <br/>Jövök a kereszthez...Az élet forrása testedbol ered.</lines>
    </verse>
    <verse name="v2">
      <lines>1.Nincsen más hely ahol megpihenhetek, nincsen más mód,<br/> hogy letegyem bunömet. Amit gondolattal, tettel,<br/>vagy szóval elkövettem Teremts újra tiszta szivet bennem!</lines>
    </verse>
    <verse name="v3">
      <lines>2. Nincsen más út, mely szabadságra vezet, <br/>Nincsen más Vér, mely elmossa bunömet.<br/>Jézus, huséges Istenem,vonj magadhoz engem! <br/>Teremts újra tiszta szivet bennem!</lines>
    </verse>
  </lyrics>
</song>
