<?xml version='1.0' encoding='UTF-8'?>
<song xmlns="http://openlyrics.info/namespace/2009/song" version="0.8" createdIn="OpenLP 2.4.6" modifiedIn="OpenLP 2.4.6" modifiedDate="2019-10-01T15:03:25">
  <properties>
    <titles>
      <title>Nikodémus</title>
    </titles>
    <authors>
      <author>Emma</author>
    </authors>
  </properties>
  <lyrics>
    <verse name="v1">
      <lines>Egy forró nyári éjjel Jeruzsálem peremén,<br/>Hol Jézus pihent szerény fekhelyén,<br/>Nagy titokban Nikodémus felkereste őt,<br/>Hogy beszélgessen kérdéseiről.</lines>
    </verse>
    <verse name="v2">
      <lines>"Mester, mi azt tudjuk, hogy te Istentől jöttél,<br/>Hogy taníts minket, azért küldettél,<br/>Ily csodákat ember fia, senki nem tehet,<br/>Csak az, aki fentről érkezett."</lines>
    </verse>
    <verse name="v3">
      <lines>"Bizony, mondom néked, ha újjászületnél,<br/>Úgy megláthatnád Isten országát!<br/>Nem visz oda másik út, hát ne is keressél,<br/>De bennem örök élet vár reád!"</lines>
    </verse>
    <verse name="v4">
      <lines>"Uram, bocsáss meg, de ezt mégsem értem én...<br/>Mondd, hogy születhet újból, aki vén?<br/>Próbálom, de józanésszel fel nem foghatom,<br/>Hogy mit jelent e furcsa fogalom."</lines>
    </verse>
    <verse name="v5">
      <lines>Én sem tudtam régen, mi az újjászületés,<br/>Bár volt bennem jó szándék, nem kevés...<br/>Mikor Jézus kézbe vette bűnös életem,<br/>A régi elmúlt, újjá lett minden...</lines>
    </verse>
    <verse name="v6">
      <lines>"Bizony, mondom néked, ha újjászülettél,<br/>Csak úgy látod meg Isten országát!<br/>Nem visz oda másik út, hát ne is keressél,<br/>De Jézusban új élet vár reád!"</lines>
    </verse>
  </lyrics>
</song>
