<?xml version='1.0' encoding='UTF-8'?>
<song xmlns="http://openlyrics.info/namespace/2009/song" version="0.8" createdIn="OpenLP 2.4.6" modifiedIn="OpenLP 2.4.6" modifiedDate="2019-10-01T15:03:27">
  <properties>
    <titles>
      <title>Tudd van egy gyertya B</title>
    </titles>
    <authors>
      <author>Author Unknown</author>
    </authors>
  </properties>
  <lyrics>
    <verse name="v1">
      <lines>Tudd, van egy gyertya a szívünkben,<br/>Van kié lobban, van kié nem.<br/>De él az Isten, ki lángra gyújthat,<br/>És meggyógyíthat, ha Benne élsz.</lines>
    </verse>
    <verse name="c1">
      <lines>Hordozd a gyertyát, lángoljon benned,<br/>Annyian várják, oly sok szív fáj...<br/>Törd át az éjjelt, hadd lássák fényed,<br/>Tartsd a gyertyát, szükség van rá,<br/>Óvd a lángját, szükség van rá.</lines>
    </verse>
    <verse name="v2">
      <lines>Eltévedt testvér, látod, hogy nem megy,<br/>Ahol kerestél, nem égett láng,<br/>Becsaptak téged, de ne add fel, kérlek,<br/>Elsszunnyadt gyertyád szikrára vár!</lines>
    </verse>
    <verse name="v3">
      <lines>Istenben bízva, a holnap hív ma,<br/>Nézzünk fel együtt az ég felé,<br/>Imában kérve, Jézus nevében<br/>Győzzük le együtt az éjszakát!</lines>
    </verse>
  </lyrics>
</song>
