<?xml version="1.0" encoding="UTF-8"?>
<song xmlns="http://openlyrics.info/namespace/2009/song" version="0.8" createdIn="ConvDiatarOpenlyrics" modifiedIn="ConvDiatarOpenlyrics" modifiedDate="2015-06-09T16:45:36">
  <properties>
    <titles>
      <title>Nagyasszonyunk, hazánk</title>
    </titles>
    <verseOrder>v1</verseOrder>
    <songbooks>
      <songbook name="Erdélyi gyűjtemény" entry="m18"/>
    </songbooks>
  </properties>
  <lyrics>
    <verse name="v1">
      <lines>Nagyasszonyunk, hazánk reménye, bús nemzeted zokogva esd.<br/>Nyújtsd irgalom, jobbod feléje, botlásiért, oh, meg ne vesd.<br/>Mi lesz belőlünk, hogyha te elhagysz, ó árvaságunk sírba hervaszt.<br/>Minden reményünk csak Te vagy, szent Szűzanyánk, szent Szűzanyánk<br/>Óh, el ne hagyj!</lines>
    </verse>
  </lyrics>
</song>
