<?xml version='1.0' encoding='UTF-8'?>
<song createdIn="OpenLP 2.0.1" modifiedDate="2015-01-20T14:23:23" modifiedIn="openlyrics.py 0.2" version="0.8" xmlns="http://openlyrics.info/namespace/2009/song">
  <properties>
    <titles>
      <title lang="hu">Gyertek, dicsérjük együtt</title>
      <title lang="he">Hava Nagila</title>
    </titles>
    <authors>
      <author type="words">Abraham Zevi Idelsohn</author>
      <author type="music">Abraham Zevi Idelsohn</author>
    </authors>
    <songbooks>
      <songbook entry="10" name="Szent András Énekfüzet" />
    </songbooks>
    <copyright>közkincs</copyright>
    <verseOrder>v1 c1</verseOrder>
  </properties>
  <lyrics>
    <verse name="v1">
      <lines>‖: Gyertek, dicsérjük együtt Izrael Szentjét,<br />mert Ő a Megváltó! :‖<br />‖: Emeld fel kezedet, nyisd meg a szívedet,<br />mert Ő a te Szabadítód! :‖</lines>
    </verse>
    <verse name="c1">
      <lines>Gyertek, gyertek!<br />Menjünk fel az Úr hegyére, vigasságnak lakhelyére,<br />ujjongjunk Őelőtte, táncoljunk Őelőtte!<br />Az Ő neve, az Ő neve: Ott lakik az Úr!</lines>
    </verse>
  </lyrics>
</song>