<?xml version="1.0" encoding="UTF-8"?>
<song xmlns="http://openlyrics.info/namespace/2009/song" version="0.8" createdIn="ConvDiatarOpenlyrics" modifiedIn="ConvDiatarOpenlyrics" modifiedDate="2015-06-09T16:46:31">
  <properties>
    <titles>
      <title>Mennyei Atya</title>
    </titles>
    <verseOrder>v1 v2 v3 v4</verseOrder>
    <songbooks>
      <songbook name="Kék könyv" entry="6"/>
    </songbooks>
  </properties>
  <lyrics>
    <verse name="v1">
      <lines>A Mennyei Atya szereti a hegyet és a völgyeket,<br/>a Mennyei Atya szereti az erdőt és a réteket,<br/>és‖: örül, mikor látja, hogyan nyílik a sok kis virág,<br/>a méhecskék szorgalmasan gyűjtik a virág porát. :‖La, la…</lines>
    </verse>
    <verse name="v2">
      <lines>A Mennyei Atya szereti a falut és a házakat,<br/>a Mennyei Atya szereti a városokat, utcákat,<br/>és‖: örül, mikor építenek, dolgoznak az emberek,<br/>de szomorú, ha azt látja, hogy egymással nem törődnek. :‖</lines>
    </verse>
    <verse name="v3">
      <lines>A Mennyei Atya legjobban az embereket szereti,<br/>a Mennyei Atya szeretetből adta ezt a világot nekik,<br/>és‖: örül, mikor látja, hogyan szeretnek az emberek,<br/>de szomorú, ha bántják egymást, gonoszak és gyűlölnek. :‖</lines>
    </verse>
    <verse name="v4">
      <lines>A Mennyei Atya legjobban a gyermekeket kedveli,<br/>a Mennyei Atya a kicsikben a kicsiséget szereti,<br/>és‖: azt mondta a felnőtteknek: „Gyerekké kell lennetek,<br/>mert országomba senki mást, csak gyermekeket engedek!” :‖</lines>
    </verse>
  </lyrics>
</song>
