<?xml version="1.0"?>
<song xmlns="http://openlyrics.info/namespace/2009/song" version="0.8" createdIn="ConvDiatarOpenlyrics" modifiedIn="ConvDiatarOpenlyrics" modifiedDate="2015-06-09T16:45:32">
  <properties>
    <titles>
      <title>Jeruzsálem gyermeknépe</title>
    </titles>
    <verseOrder>v1</verseOrder>
    <authors>
      <author></author>
    </authors>
    <songbooks>
      <songbook name="Éneklő Egyház" entry="804"/>
    </songbooks>
  </properties>
  <lyrics>
    <verse name="v1">
      <lines>Jeruzsálem gyermeknépe<br/>leterítetvén ruháit az útra,<br/>nagy szóval így kiáltott:<br/>Hozsanna Dávid Fiának,<br/>áldott, ki jő az Úr nevében!</lines>
    </verse>
  </lyrics>
</song>
