<?xml version="1.0"?>
<song xmlns="http://openlyrics.info/namespace/2009/song" version="0.8" createdIn="ConvDiatarOpenlyrics" modifiedIn="ConvDiatarOpenlyrics" modifiedDate="2014-05-23T15:27:14">
  <properties>
    <titles>
      <title>Templomodba jöttünk buzg</title>
    </titles>
    <verseOrder>v1 v2 v3 v4 v5 v6</verseOrder>
    <authors>
      <author></author>
    </authors>
    <songbooks>
      <songbook name="Éneklő Egyház" entry="114"/>
    </songbooks>
  </properties>
  <lyrics>
    <verse name="v1">
      <lines>Templomodba jöttünk buzgó szeretettel,<br/>mint a szent asszonyok illatos kenettel;<br/>áldunk téged húsvéti örömmel.<br/>Alleluja, alleluja, hála néked, világ Megváltója.</lines>
    </verse>
    <verse name="v2">
      <lines>Nem keres már Júdás, üldöző sereggel,<br/>hanem a szent Egyház, ünneplő menettel,<br/>hódol néked vigadozó szívvel.<br/>Alleluja, alleluja, hála néked, világ Megváltója.</lines>
    </verse>
    <verse name="v3">
      <lines>Megszégyenült immár Kaifás és Annás,<br/>Jézus fényes arcát nem sérti már csapás,<br/>nem csókolja képmutató Júdás.<br/>Alleluja, alleluja, hála néked, világ Megváltója.</lines>
    </verse>
    <verse name="v4">
      <lines>Siet hozzá Péter égő szeretettel,<br/>örömét vegyíti bűnbánó könnyekkel,<br/>jó Mesterét látván szemeivel.<br/>Alleluja, alleluja, hála néked, világ Megváltója.</lines>
    </verse>
    <verse name="v5">
      <lines>Fölemelte Jézus az áldott keresztfát,<br/>győzelmével ékes tündöklő zászlaját,<br/>megdöntötte a Sátán hatalmát.<br/>Alleluja, alleluja, hála néked, világ Megváltója.</lines>
    </verse>
    <verse name="v6">
      <lines>Dicsőséges Fiát mennyei szent Atyja<br/>a megváltott népnek fényesen mutatja:<br/>ím a Húsvét igaz áldozatja!<br/>Alleluja, alleluja, hála néked, világ Megváltója.</lines>
    </verse>
  </lyrics>
</song>
