<?xml version="1.0"?>
<song xmlns="http://openlyrics.info/namespace/2009/song" version="0.8" createdIn="ConvDiatarOpenlyrics" modifiedIn="ConvDiatarOpenlyrics" modifiedDate="2014-05-23T15:27:17">
  <properties>
    <titles>
      <title>Íme, megváltásunk szent titka</title>
    </titles>
    <verseOrder>v1</verseOrder>
    <authors>
      <author></author>
    </authors>
    <songbooks>
      <songbook name="Éneklő Egyház" entry="406"/>
    </songbooks>
  </properties>
  <lyrics>
    <verse name="v1">
      <lines>Íme, megváltásunk szent titka!<br/>Valahányszor esszük ezt a kenyeret és iszunk ebből a kehelyből,<br/>halálodat hirdetjük, Urunk,<br/>amíg el nem jössz.</lines>
    </verse>
  </lyrics>
</song>
