<?xml version="1.0" encoding="UTF-8"?>
<song xmlns="http://openlyrics.info/namespace/2009/song" version="0.8" createdIn="ConvDiatarOpenlyrics" modifiedIn="ConvDiatarOpenlyrics" modifiedDate="2015-06-09T16:47:27">
  <properties>
    <titles>
      <title>Édes Jézus, neked élek</title>
    </titles>
    <verseOrder>v1</verseOrder>
    <authors>
      <author></author>
    </authors>
    <songbooks>
      <songbook name="Szent Vagy, Uram!" entry="113"/>
    </songbooks>
  </properties>
  <lyrics>
    <verse name="v1">
      <lines>Édes Jézus, neked élek.<br/>Édes Jézus, neked halok,<br/>Életemben, halálomban,<br/>Édes Jézus, tied vagyok.</lines>
    </verse>
  </lyrics>
</song>
